djicons/__init__.py
djicons/apps.py
djicons/cache.py
djicons/conf.py
djicons/icon.py
djicons/registry.py
djicons/scanner.py
djicons/contrib/__init__.py
djicons/contrib/erplora.py
djicons/loaders/__init__.py
djicons/loaders/base.py
djicons/loaders/cdn.py
djicons/loaders/directory.py
djicons/management/__init__.py
djicons/management/commands/__init__.py
djicons/management/commands/djicons_collect.py
djicons/packs/__init__.py
djicons/packs/fontawesome/__init__.py
djicons/packs/fontawesome/icons/.gitkeep
djicons/packs/heroicons/__init__.py
djicons/packs/heroicons/icons/.gitkeep
djicons/packs/ionicons/__init__.py
djicons/packs/ionicons/icons/.gitkeep
djicons/packs/lucide/__init__.py
djicons/packs/lucide/icons/.gitkeep
djicons/packs/material/__init__.py
djicons/packs/material/icons/.gitkeep
djicons/packs/tabler/__init__.py
djicons/packs/tabler/icons/.gitkeep
djicons/templatetags/__init__.py
djicons/templatetags/djicons.py
djicons-0.2.2.dist-info/METADATA
djicons-0.2.2.dist-info/WHEEL
djicons-0.2.2.dist-info/licenses/LICENSE
djicons-0.2.2.dist-info/RECORD
