Metadata-Version: 2.4
Name: djicons
Version: 0.2.2
Summary: Multi-library SVG icon system for Django - like react-icons, but backend-driven
Project-URL: Homepage, https://github.com/djicons/djicons
Project-URL: Documentation, https://github.com/djicons/djicons#readme
Project-URL: Repository, https://github.com/djicons/djicons
Project-URL: Issues, https://github.com/djicons/djicons/issues
Project-URL: Changelog, https://github.com/djicons/djicons/blob/main/CHANGELOG.md
Author-email: Ioan Beilic <ioanbeilic@gmail.com>
License-Expression: MIT
License-File: LICENSE
Keywords: django,heroicons,icons,ionicons,lucide,material,svg,tabler,template-tags
Classifier: Development Status :: 4 - Beta
Classifier: Environment :: Web Environment
Classifier: Framework :: Django
Classifier: Framework :: Django :: 4.2
Classifier: Framework :: Django :: 5.0
Classifier: Framework :: Django :: 5.1
Classifier: Intended Audience :: Developers
Classifier: License :: OSI Approved :: MIT License
Classifier: Operating System :: OS Independent
Classifier: Programming Language :: Python :: 3
Classifier: Programming Language :: Python :: 3.10
Classifier: Programming Language :: Python :: 3.11
Classifier: Programming Language :: Python :: 3.12
Classifier: Programming Language :: Python :: 3.13
Classifier: Topic :: Internet :: WWW/HTTP
Classifier: Topic :: Software Development :: Libraries :: Python Modules
Requires-Python: >=3.10
Requires-Dist: django>=4.2
Provides-Extra: dev
Requires-Dist: django-stubs>=4.0; extra == 'dev'
Requires-Dist: mypy>=1.0; extra == 'dev'
Requires-Dist: pytest-cov>=4.0; extra == 'dev'
Requires-Dist: pytest-django>=4.5; extra == 'dev'
Requires-Dist: pytest>=8.0; extra == 'dev'
Requires-Dist: ruff>=0.1; extra == 'dev'
